actus/__init__.py
actus/_annotations.py
actus/_highlighting.py
actus/_log_section.py
actus/_style.py
actus-0.7.1.dist-info/METADATA
actus-0.7.1.dist-info/WHEEL
actus-0.7.1.dist-info/licenses/LICENSE.txt
actus-0.7.1.dist-info/RECORD
