Metadata-Version: 2.3
Name: actus
Version: 0.7.1
Summary: A logging library for python development
Author-email: Havsalt <knutolaihelgesen@gmail.com>
License: MIT
License-File: LICENSE.txt
Requires-Python: >=3.10
Requires-Dist: colex~=0.2.0
